docs_to_md/__init__.py
docs_to_md/jina.py
docs_to_md/main.py
docs_to_md/parser.py
docs_to_md/utils.py
docs_to_md-0.1.2.dist-info/METADATA
docs_to_md-0.1.2.dist-info/WHEEL
docs_to_md-0.1.2.dist-info/entry_points.txt
docs_to_md-0.1.2.dist-info/licenses/LICENSE
docs_to_md-0.1.2.dist-info/RECORD
