Metadata-Version: 2.3
Name: docs-to-md
Version: 0.1.2
Summary: Convert readthedocs to markdown
Author-email: ackness <ackness8@gmail.com>
License-File: LICENSE
Requires-Python: >=3.10
Requires-Dist: click>=8.1.7
Requires-Dist: httpx>=0.27.2
Requires-Dist: lxml>=5.3.0
Requires-Dist: openai>=1.50.0
Requires-Dist: requests>=2.32.3
Requires-Dist: setuptools>=75.1.0
Requires-Dist: tqdm>=4.66.5
